HISTORY.rst
LICENSE
MANIFEST.in
README.rst
requirements.txt
setup.cfg
setup.py
liquepy/__about__.py
liquepy/__init__.py
liquepy/_spatial_models.py
liquepy/exceptions.py
liquepy/functions.py
liquepy.egg-info/PKG-INFO
liquepy.egg-info/SOURCES.txt
liquepy.egg-info/dependency_links.txt
liquepy.egg-info/not-zip-safe
liquepy.egg-info/requires.txt
liquepy.egg-info/top_level.txt
liquepy/element/__init__.py
liquepy/element/assess.py
liquepy/element/correlations.py
liquepy/element/models.py
liquepy/esp/__init__.py
liquepy/esp/millen_2020.py
liquepy/field/__init__.py
liquepy/field/correlations.py
liquepy/field/cpt_file.py
liquepy/field/nzgd_cpt_converter.py
liquepy/field/transect.py
liquepy/fig/__init__.py
liquepy/fig/figures_field_and_trigger.py
liquepy/motion/__init__.py
liquepy/motion/loader.py
liquepy/motion/measures.py
liquepy/num/__init__.py
liquepy/num/flac.py
liquepy/num/general.py
liquepy/num/models.py
liquepy/num/mrd_curves.py
liquepy/num/o3.py
liquepy/settlement/__init__.py
liquepy/settlement/methods.py
liquepy/soil/__init__.py
liquepy/soil/properties.py
liquepy/spatial/__init__.py
liquepy/spatial/map_coords.py
liquepy/sra/__init__.py
liquepy/sra/elsa.py
liquepy/sra/sra.py
liquepy/sra/strain_curves.py
liquepy/sra/theory.py
liquepy/trigger/__init__.py
liquepy/trigger/boulanger_and_idriss_2014.py
liquepy/trigger/ib2008.py
liquepy/trigger/nses.py
liquepy/trigger/shear_strain.py
liquepy/trigger/triggering_measures.py
liquepy/trigger/volumetric_strain.py