Metadata-Version: 2.1
Name: liquepy
Version: 0.6.28
Summary: Tools for soil liquefaction analysis
Home-page: https://github.com/eng-tools/liquepy
Author: Maxim Millen and Julieth Quintero
Author-email: mmi46@uclive.ac.nz
License: MIT
Keywords: geotechnical engineering foundations settlement
Platform: UNKNOWN
Classifier: Development Status :: 4 - Beta
Classifier: Intended Audience :: Science/Research
Classifier: Topic :: Scientific/Engineering
Classifier: License :: OSI Approved :: MIT License
Classifier: Programming Language :: Python :: 3
Requires-Python: >=3
Provides-Extra: test
Provides-Extra: maps
Provides-Extra: sra
Provides-Extra: fig
License-File: LICENSE
